py_event_studies/__init__.py
py_event_studies/_ar_statistic_tests.py
py_event_studies/_calibration.py
py_event_studies/_car_statistic_tests.py
py_event_studies/_data_loader.py
py_event_studies/_utils.py
py_event_studies/api.py
py_event_studies/data_storage.py
py_event_studies/results.py
py_event_studies-0.3.0.dist-info/METADATA
py_event_studies-0.3.0.dist-info/WHEEL
py_event_studies-0.3.0.dist-info/RECORD
