Metadata-Version: 2.1
Name: py_event_studies
Version: 0.3.0
Summary: Event Studies Package for CRSP
Author: Rémi Genet
Requires-Python: >=3.9,<3.13
Classifier: Programming Language :: Python :: 3
Classifier: Programming Language :: Python :: 3.9
Classifier: Programming Language :: Python :: 3.10
Classifier: Programming Language :: Python :: 3.11
Classifier: Programming Language :: Python :: 3.12
Requires-Dist: joblib (>=1.4.2,<2.0.0)
Requires-Dist: matplotlib (>=3.8,<4.0)
Requires-Dist: numba (>=0.60.0)
Requires-Dist: numpy (>=1.2,<3.0)
Requires-Dist: pandas (>=2.0.0,<3.0.0)
Requires-Dist: pyarrow (>=17.0.0,<18.0.0)
Requires-Dist: scikit-learn (>=1.5.1,<2.0.0)
